<ParameterList>
  <Parameter name="Amanzi Input Format Version" type="string" value="1.2.1"/>
  <ParameterList name="General Description">
    <Parameter name="model_name" type="string" value="Rifle 2D Unsaturated TT-01 / TT-02 / TT-03 transect"/>
    <Parameter name="comments" type="string" value="Fill + Alluvium on top of Wasatch in 2D"/>
    <Parameter name="model_id" type="string" value="rifle_u2d"/>
    <Parameter name="author" type="string" value="Sergi Molins, Bhavna Arora, Jeff Johnson"/>
  </ParameterList>
  <ParameterList name="Mesh">
    <ParameterList name="Unstructured">
      <ParameterList name="Expert">
        <Parameter name="Framework" type="string" value="MSTK"/>
      </ParameterList>
      <ParameterList name="Read Mesh File">
        <Parameter name="File" type="string" value="rifle.exo"/>
        <Parameter name="Format" type="string" value="Exodus II"/>
      </ParameterList>
    </ParameterList>
  </ParameterList>
  <ParameterList name="Domain">
    <Parameter name="Spatial Dimension" type="int" value="2"/>
  </ParameterList>
  <ParameterList name="Execution Control">
    <Parameter name="Flow Model" type="string" value="Richards"/>
    <Parameter name="Transport Model" type="string" value="On"/>
    <Parameter name="Chemistry Model" type="string" value="Alquimia"/>
    <Parameter name="Verbosity" type="string" value="high"/>
    <ParameterList name="Time Integration Mode">
      <ParameterList name="Initialize To Steady">
        <Parameter name="Start" type="double" value="0e-17"/>
        <Parameter name="Switch" type="double" value="8640000.00000000000"/>
        <Parameter name="Steady Initial Time Step" type="double" value="1000.00000000000000"/>
        <Parameter name="End" type="double" value="6.6262e+8"/>
        <!--"4.74421e8"/> -->
        <!--6.6262E+08 sec = 20 years -->
        <!--"8.75e+06"/>-->
        <!-- "4.73364000000000000e+08"/> -->
        <Parameter name="Transient Initial Time Step" type="double" value="10.0000000000000000"/>
      </ParameterList>
    </ParameterList>
    <ParameterList name="Numerical Control Parameters">
      <ParameterList name="Unstructured Algorithm">
        <ParameterList name="Steady-State Implicit Time Integration">
          <Parameter name="steady timestep reduction factor" type="double" value="0.100000000000000006"/>
          <Parameter name="steady timestep increase factor" type="double" value="1.25000000000000000"/>
          <Parameter name="steady min iterations" type="int" value="10"/>
          <Parameter name="steady max iterations" type="int" value="15"/>
          <Parameter name="steady max preconditioner lag iterations" type="int" value="30"/>
          <Parameter name="steady nonlinear tolerance" type="double" value="0.0000100000000000000008"/>
          <Parameter name="steady max timestep" type="double" value="3155759.99999999953"/>
          <Parameter name="steady preconditioner" type="string" value="Hypre AMG"/>
        </ParameterList>
        <ParameterList name="Transient Implicit Time Integration">
          <Parameter name="transient min iterations" type="int" value="10"/>
          <Parameter name="transient max iterations" type="int" value="15"/>
          <Parameter name="transient max preconditioner lag iterations" type="int" value="5"/>
          <Parameter name="transient timestep increase factor" type="double" value="1.25000000000000000"/>
          <Parameter name="transient timestep reduction factor" type="double" value="0.500000000000000000"/>
          <Parameter name="transient max timestep" type="double" value="10000000.0000000000"/>
        </ParameterList>
        <ParameterList name="Linear Solver">
          <Parameter name="linear solver preconditioner" type="string" value="gmres"/>
          <Parameter name="linear solver maximum iterations" type="int" value="50"/>
          <Parameter name="linear solver tolerance" type="double" value="1.00000000000000007e-18"/>
        </ParameterList>
        <ParameterList name="Preconditioners">
          <ParameterList name="Hypre AMG">
            <Parameter name="Hypre AMG cycle applications" type="int" value="5"/>
            <Parameter name="Hypre AMG smoother sweeps" type="int" value="3"/>
            <Parameter name="Hypre AMG tolerance" type="double" value="0e-17"/>
            <Parameter name="Hypre AMG strong threshold" type="double" value="0.400000000000000022"/>
          </ParameterList>
        </ParameterList>
        <ParameterList name="Flow Process Kernel">
        </ParameterList>
        <ParameterList name="Transport Process Kernel">
          <Parameter name="Transport Integration Algorithm" type="string" value="Explicit First-Order"/>
          <Parameter name="transport subcycling" type="bool" value="true"/>
        </ParameterList>
      </ParameterList>
    </ParameterList>
    <!--   <ParameterList name="Restart from Checkpoint Data File">
      <Parameter name="Checkpoint Data File Name" type="string" value="chk00145.h5"/>
    </ParameterList> -->
  </ParameterList>
  <ParameterList name="Phase Definitions">
    <ParameterList name="Aqueous">
      <ParameterList name="Phase Properties">
        <ParameterList name="Viscosity: Uniform">
          <Parameter name="Viscosity" type="double" value="0.00100200000000000007"/>
        </ParameterList>
        <ParameterList name="Density: Uniform">
          <Parameter name="Density" type="double" value="998.200000000000045"/>
        </ParameterList>
      </ParameterList>
      <ParameterList name="Phase Components">
        <ParameterList name="water">
          <Parameter name="Component Solutes" type="Array(string)" value="{H+, Cl-, SO4--, HCO3-, SiO2(aq), Al+++, Ca++, Mg++, Fe++, Fe+++, K+, Na+, O2(aq), HS-, NO3-, NO2-, N2(aq), Ac-, NH3(aq), Tracer}"/>
        </ParameterList>
      </ParameterList>
    </ParameterList>
    <ParameterList name="Solid">
      <Parameter name="Minerals" type="Array(string)" value="{Goethite, Calcite, Siderite, Pyrite, Cellulose}"/>
    </ParameterList>
  </ParameterList>
  <ParameterList name="Regions">
    <ParameterList name="alluvium">
      <ParameterList name="Region: Labeled Set">
        <Parameter name="File" type="string" value="rifle.exo"/>
        <Parameter name="Label" type="string" value="2"/>
        <Parameter name="Format" type="string" value="Exodus II"/>
        <Parameter name="Entity" type="string" value="cell"/>
      </ParameterList>
    </ParameterList>
    <ParameterList name="fill">
      <ParameterList name="Region: Labeled Set">
        <Parameter name="File" type="string" value="rifle.exo"/>
        <Parameter name="Label" type="string" value="1"/>
        <Parameter name="Format" type="string" value="Exodus II"/>
        <Parameter name="Entity" type="string" value="cell"/>
      </ParameterList>
    </ParameterList>
    <ParameterList name="surface">
      <ParameterList name="Region: Labeled Set">
        <Parameter name="File" type="string" value="rifle.exo"/>
        <Parameter name="Label" type="string" value="2"/>
        <Parameter name="Format" type="string" value="Exodus II"/>
        <Parameter name="Entity" type="string" value="face"/>
      </ParameterList>
    </ParameterList>
    <ParameterList name="left">
      <ParameterList name="Region: Labeled Set">
        <Parameter name="File" type="string" value="rifle.exo"/>
        <Parameter name="Label" type="string" value="5"/>
        <Parameter name="Format" type="string" value="Exodus II"/>
        <Parameter name="Entity" type="string" value="face"/>
      </ParameterList>
    </ParameterList>
    <ParameterList name="right">
      <ParameterList name="Region: Labeled Set">
        <Parameter name="File" type="string" value="rifle.exo"/>
        <Parameter name="Label" type="string" value="3"/>
        <Parameter name="Format" type="string" value="Exodus II"/>
        <Parameter name="Entity" type="string" value="face"/>
      </ParameterList>
    </ParameterList>
  </ParameterList>
  <ParameterList name="Material Properties">
    <ParameterList name="loam">
      <ParameterList name="Porosity: Uniform">
        <Parameter name="Value" type="double" value="0.205999999999999989"/>
      </ParameterList>
      <ParameterList name="Particle Density: Uniform">
        <Parameter name="Value" type="double" value="2720.00000000000000"/>
      </ParameterList>
      <ParameterList name="Intrinsic Permeability: Uniform">
        <Parameter name="Value" type="double" value="4.52399999999999971e-12"/>
      </ParameterList>
      <Parameter name="Assigned Regions" type="Array(string)" value="{fill}"/>
      <ParameterList name="Capillary Pressure: van Genuchten">
        <Parameter name="alpha" type="double" value="0.000506999999999999964"/>
        <Parameter name="m" type="double" value="0.177999999999999992"/>
        <Parameter name="Sr" type="double" value="0.0728000000000000036"/>
        <Parameter name="Relative Permeability" type="string" value="Mualem"/>
      </ParameterList>
      <ParameterList name="Mineralogy">
        <ParameterList name="Goethite">
          <Parameter name="Volume Fraction" type="double" value="0.0"/>
          <Parameter name="Specific Surface Area" type="double" value="0.1"/>
        </ParameterList>
        <ParameterList name="Calcite">
          <Parameter name="Volume Fraction" type="double" value="0.88"/>
          <Parameter name="Specific Surface Area" type="double" value="3262.3"/>
        </ParameterList>
        <ParameterList name="Siderite">
          <Parameter name="Volume Fraction" type="double" value="0.0"/>
          <Parameter name="Specific Surface Area" type="double" value="0.1"/>
        </ParameterList>
        <ParameterList name="Pyrite">
          <Parameter name="Volume Fraction" type="double" value="0.0"/>
          <Parameter name="Specific Surface Area" type="double" value="0.1"/>
        </ParameterList>
        <ParameterList name="Cellulose">
          <Parameter name="Volume Fraction" type="double" value="0.0"/>
          <Parameter name="Specific Surface Area" type="double" value="0.1"/>
        </ParameterList>
      </ParameterList>
      <!-- Mineralogy -->
    </ParameterList>
    <ParameterList name="sand">
      <ParameterList name="Porosity: Uniform">
        <Parameter name="Value" type="double" value="0.197899999999999993"/>
      </ParameterList>
      <ParameterList name="Particle Density: Uniform">
        <Parameter name="Value" type="double" value="2720.00000000000000"/>
      </ParameterList>
      <ParameterList name="Intrinsic Permeability: Anisotropic Uniform">
        <Parameter name="x" type="double" value="9.67000000000000060e-12"/>
        <Parameter name="y" type="double" value="9.76000000000000042e-12"/>
      </ParameterList>
      <Parameter name="Assigned Regions" type="Array(string)" value="{alluvium}"/>
      <ParameterList name="Capillary Pressure: van Genuchten">
        <Parameter name="alpha" type="double" value="0.000846100000000000020"/>
        <Parameter name="m" type="double" value="0.305999999999999994"/>
        <Parameter name="Sr" type="double" value="0.126299999999999996"/>
        <Parameter name="Relative Permeability" type="string" value="Mualem"/>
      </ParameterList>
      <ParameterList name="Mineralogy">
        <ParameterList name="Goethite">
          <Parameter name="Volume Fraction" type="double" value="0.0"/>
          <Parameter name="Specific Surface Area" type="double" value="0.1"/>
        </ParameterList>
        <ParameterList name="Calcite">
          <Parameter name="Volume Fraction" type="double" value="0.88"/>
          <Parameter name="Specific Surface Area" type="double" value="3262.3"/>
        </ParameterList>
        <ParameterList name="Siderite">
          <Parameter name="Volume Fraction" type="double" value="0.0"/>
          <Parameter name="Specific Surface Area" type="double" value="0.1"/>
        </ParameterList>
        <ParameterList name="Pyrite">
          <Parameter name="Volume Fraction" type="double" value="0.0"/>
          <Parameter name="Specific Surface Area" type="double" value="0.1"/>
        </ParameterList>
        <ParameterList name="Cellulose">
          <Parameter name="Volume Fraction" type="double" value="0.0"/>
          <Parameter name="Specific Surface Area" type="double" value="0.1"/>
        </ParameterList>
      </ParameterList>
      <!-- Mineralogy -->
    </ParameterList>
  </ParameterList>
  <ParameterList name="Initial Conditions">
    <ParameterList name="Pressure and concentration for fill">
      <Parameter name="Assigned Regions" type="Array(string)" value="{fill}"/>
      <ParameterList name="IC: Uniform Pressure">
        <Parameter name="Phase" type="string" value="Aqueous"/>
        <Parameter name="Value" type="double" value="101325.000000000000"/>
      </ParameterList>
      <ParameterList name="Solute IC">
        <ParameterList name="Aqueous">
          <ParameterList name="water">
            <ParameterList name="H+">
              <ParameterList name="IC: Uniform Concentration">
                <Parameter name="Geochemical Condition" type="string" value="oxidized"/>
              </ParameterList>
              <Parameter name="Concentration Units" type="string" value="Molarity"/>
            </ParameterList>
            <ParameterList name="Cl-">
              <ParameterList name="IC: Uniform Concentration">
                <Parameter name="Geochemical Condition" type="string" value="oxidized"/>
              </ParameterList>
              <Parameter name="Concentration Units" type="string" value="Molarity"/>
            </ParameterList>
            <ParameterList name="SO4--">
              <ParameterList name="IC: Uniform Concentration">
                <Parameter name="Geochemical Condition" type="string" value="oxidized"/>
              </ParameterList>
              <Parameter name="Concentration Units" type="string" value="Molarity"/>
            </ParameterList>
            <ParameterList name="HCO3-">
              <ParameterList name="IC: Uniform Concentration">
                <Parameter name="Geochemical Condition" type="string" value="oxidized"/>
              </ParameterList>
              <Parameter name="Concentration Units" type="string" value="Molarity"/>
            </ParameterList>
            <ParameterList name="SiO2(aq)">
              <ParameterList name="IC: Uniform Concentration">
                <Parameter name="Geochemical Condition" type="string" value="oxidized"/>
              </ParameterList>
              <Parameter name="Concentration Units" type="string" value="Molarity"/>
            </ParameterList>
            <ParameterList name="Al+++">
              <ParameterList name="IC: Uniform Concentration">
                <Parameter name="Geochemical Condition" type="string" value="oxidized"/>
              </ParameterList>
              <Parameter name="Concentration Units" type="string" value="Molarity"/>
            </ParameterList>
            <ParameterList name="Ca++">
              <ParameterList name="IC: Uniform Concentration">
                <Parameter name="Geochemical Condition" type="string" value="oxidized"/>
              </ParameterList>
              <Parameter name="Concentration Units" type="string" value="Molarity"/>
            </ParameterList>
            <ParameterList name="Mg++">
              <ParameterList name="IC: Uniform Concentration">
                <Parameter name="Geochemical Condition" type="string" value="oxidized"/>
              </ParameterList>
              <Parameter name="Concentration Units" type="string" value="Molarity"/>
            </ParameterList>
            <ParameterList name="Fe++">
              <ParameterList name="IC: Uniform Concentration">
                <Parameter name="Geochemical Condition" type="string" value="oxidized"/>
              </ParameterList>
              <Parameter name="Concentration Units" type="string" value="Molarity"/>
            </ParameterList>
            <ParameterList name="Fe+++">
              <ParameterList name="IC: Uniform Concentration">
                <Parameter name="Geochemical Condition" type="string" value="oxidized"/>
              </ParameterList>
              <Parameter name="Concentration Units" type="string" value="Molarity"/>
            </ParameterList>
            <ParameterList name="K+">
              <ParameterList name="IC: Uniform Concentration">
                <Parameter name="Geochemical Condition" type="string" value="oxidized"/>
              </ParameterList>
              <Parameter name="Concentration Units" type="string" value="Molarity"/>
            </ParameterList>
            <ParameterList name="Na+">
              <ParameterList name="IC: Uniform Concentration">
                <Parameter name="Geochemical Condition" type="string" value="oxidized"/>
              </ParameterList>
              <Parameter name="Concentration Units" type="string" value="Molarity"/>
            </ParameterList>
            <ParameterList name="O2(aq)">
              <ParameterList name="IC: Uniform Concentration">
                <Parameter name="Geochemical Condition" type="string" value="oxidized"/>
              </ParameterList>
              <Parameter name="Concentration Units" type="string" value="Molarity"/>
            </ParameterList>
            <ParameterList name="HS-">
              <ParameterList name="IC: Uniform Concentration">
                <Parameter name="Geochemical Condition" type="string" value="oxidized"/>
              </ParameterList>
              <Parameter name="Concentration Units" type="string" value="Molarity"/>
            </ParameterList>
            <ParameterList name="NO3-">
              <ParameterList name="IC: Uniform Concentration">
                <Parameter name="Geochemical Condition" type="string" value="oxidized"/>
              </ParameterList>
              <Parameter name="Concentration Units" type="string" value="Molarity"/>
            </ParameterList>
            <ParameterList name="NO2-">
              <ParameterList name="IC: Uniform Concentration">
                <Parameter name="Geochemical Condition" type="string" value="oxidized"/>
              </ParameterList>
              <Parameter name="Concentration Units" type="string" value="Molarity"/>
            </ParameterList>
            <ParameterList name="N2(aq)">
              <ParameterList name="IC: Uniform Concentration">
                <Parameter name="Geochemical Condition" type="string" value="oxidized"/>
              </ParameterList>
              <Parameter name="Concentration Units" type="string" value="Molarity"/>
            </ParameterList>
            <ParameterList name="Ac-">
              <ParameterList name="IC: Uniform Concentration">
                <Parameter name="Geochemical Condition" type="string" value="oxidized"/>
              </ParameterList>
              <Parameter name="Concentration Units" type="string" value="Molarity"/>
            </ParameterList>
            <ParameterList name="NH3(aq)">
              <ParameterList name="IC: Uniform Concentration">
                <Parameter name="Geochemical Condition" type="string" value="oxidized"/>
              </ParameterList>
              <Parameter name="Concentration Units" type="string" value="Molarity"/>
            </ParameterList>
            <ParameterList name="Tracer">
              <ParameterList name="IC: Uniform Concentration">
                <Parameter name="Geochemical Condition" type="string" value="oxidized"/>
              </ParameterList>
              <Parameter name="Concentration Units" type="string" value="Molarity"/>
            </ParameterList>
          </ParameterList>
        </ParameterList>
      </ParameterList>
    </ParameterList>
    <!--fill-->
    <ParameterList name="Pressure and concentration for alluvium">
      <Parameter name="Assigned Regions" type="Array(string)" value="{alluvium}"/>
      <ParameterList name="IC: Uniform Pressure">
        <Parameter name="Phase" type="string" value="Aqueous"/>
        <Parameter name="Value" type="double" value="101325.000000000000"/>
      </ParameterList>
      <ParameterList name="Solute IC">
        <ParameterList name="Aqueous">
          <ParameterList name="water">
            <ParameterList name="H+">
              <ParameterList name="IC: Uniform Concentration">
                <Parameter name="Geochemical Condition" type="string" value="reduced"/>
              </ParameterList>
              <Parameter name="Concentration Units" type="string" value="Molarity"/>
            </ParameterList>
            <ParameterList name="Cl-">
              <ParameterList name="IC: Uniform Concentration">
                <Parameter name="Geochemical Condition" type="string" value="reduced"/>
              </ParameterList>
              <Parameter name="Concentration Units" type="string" value="Molarity"/>
            </ParameterList>
            <ParameterList name="SO4--">
              <ParameterList name="IC: Uniform Concentration">
                <Parameter name="Geochemical Condition" type="string" value="reduced"/>
              </ParameterList>
              <Parameter name="Concentration Units" type="string" value="Molarity"/>
            </ParameterList>
            <ParameterList name="HCO3-">
              <ParameterList name="IC: Uniform Concentration">
                <Parameter name="Geochemical Condition" type="string" value="reduced"/>
              </ParameterList>
              <Parameter name="Concentration Units" type="string" value="Molarity"/>
            </ParameterList>
            <ParameterList name="SiO2(aq)">
              <ParameterList name="IC: Uniform Concentration">
                <Parameter name="Geochemical Condition" type="string" value="reduced"/>
              </ParameterList>
              <Parameter name="Concentration Units" type="string" value="Molarity"/>
            </ParameterList>
            <ParameterList name="Al+++">
              <ParameterList name="IC: Uniform Concentration">
                <Parameter name="Geochemical Condition" type="string" value="reduced"/>
              </ParameterList>
              <Parameter name="Concentration Units" type="string" value="Molarity"/>
            </ParameterList>
            <ParameterList name="Ca++">
              <ParameterList name="IC: Uniform Concentration">
                <Parameter name="Geochemical Condition" type="string" value="reduced"/>
              </ParameterList>
              <Parameter name="Concentration Units" type="string" value="Molarity"/>
            </ParameterList>
            <ParameterList name="Mg++">
              <ParameterList name="IC: Uniform Concentration">
                <Parameter name="Geochemical Condition" type="string" value="reduced"/>
              </ParameterList>
              <Parameter name="Concentration Units" type="string" value="Molarity"/>
            </ParameterList>
            <ParameterList name="Fe++">
              <ParameterList name="IC: Uniform Concentration">
                <Parameter name="Geochemical Condition" type="string" value="reduced"/>
              </ParameterList>
              <Parameter name="Concentration Units" type="string" value="Molarity"/>
            </ParameterList>
            <ParameterList name="Fe+++">
              <ParameterList name="IC: Uniform Concentration">
                <Parameter name="Geochemical Condition" type="string" value="reduced"/>
              </ParameterList>
              <Parameter name="Concentration Units" type="string" value="Molarity"/>
            </ParameterList>
            <ParameterList name="K+">
              <ParameterList name="IC: Uniform Concentration">
                <Parameter name="Geochemical Condition" type="string" value="reduced"/>
              </ParameterList>
              <Parameter name="Concentration Units" type="string" value="Molarity"/>
            </ParameterList>
            <ParameterList name="Na+">
              <ParameterList name="IC: Uniform Concentration">
                <Parameter name="Geochemical Condition" type="string" value="reduced"/>
              </ParameterList>
              <Parameter name="Concentration Units" type="string" value="Molarity"/>
            </ParameterList>
            <ParameterList name="O2(aq)">
              <ParameterList name="IC: Uniform Concentration">
                <Parameter name="Geochemical Condition" type="string" value="reduced"/>
              </ParameterList>
              <Parameter name="Concentration Units" type="string" value="Molarity"/>
            </ParameterList>
            <ParameterList name="HS-">
              <ParameterList name="IC: Uniform Concentration">
                <Parameter name="Geochemical Condition" type="string" value="reduced"/>
              </ParameterList>
              <Parameter name="Concentration Units" type="string" value="Molarity"/>
            </ParameterList>
            <ParameterList name="NO3-">
              <ParameterList name="IC: Uniform Concentration">
                <Parameter name="Geochemical Condition" type="string" value="reduced"/>
              </ParameterList>
              <Parameter name="Concentration Units" type="string" value="Molarity"/>
            </ParameterList>
            <ParameterList name="NO2-">
              <ParameterList name="IC: Uniform Concentration">
                <Parameter name="Geochemical Condition" type="string" value="reduced"/>
              </ParameterList>
              <Parameter name="Concentration Units" type="string" value="Molarity"/>
            </ParameterList>
            <ParameterList name="N2(aq)">
              <ParameterList name="IC: Uniform Concentration">
                <Parameter name="Geochemical Condition" type="string" value="reduced"/>
              </ParameterList>
              <Parameter name="Concentration Units" type="string" value="Molarity"/>
            </ParameterList>
            <ParameterList name="Ac-">
              <ParameterList name="IC: Uniform Concentration">
                <Parameter name="Geochemical Condition" type="string" value="reduced"/>
              </ParameterList>
              <Parameter name="Concentration Units" type="string" value="Molarity"/>
            </ParameterList>
            <ParameterList name="NH3(aq)">
              <ParameterList name="IC: Uniform Concentration">
                <Parameter name="Geochemical Condition" type="string" value="reduced"/>
              </ParameterList>
              <Parameter name="Concentration Units" type="string" value="Molarity"/>
            </ParameterList>
            <ParameterList name="Tracer">
              <ParameterList name="IC: Uniform Concentration">
                <Parameter name="Geochemical Condition" type="string" value="reduced"/>
              </ParameterList>
              <Parameter name="Concentration Units" type="string" value="Molarity"/>
            </ParameterList>
          </ParameterList>
        </ParameterList>
      </ParameterList>
    </ParameterList>
    <!--alluvium-->
  </ParameterList>
  <!-- Initial conditions -->
  <ParameterList name="Boundary Conditions">
    <ParameterList name="Recharge at top of the domain with ponding">
      <Parameter name="Assigned Regions" type="Array(string)" value="{surface}"/>
      <ParameterList name="BC: Flux">
        <Parameter name="Times" type="Array(double)" value="{0e-17, 473364001.000000000}"/>
        <Parameter name="Time Functions" type="Array(string)" value="{Constant}"/>
        <Parameter name="Inward Mass Flux" type="Array(double)" value="{9.49599999999999980e-7, 9.49599999999999980e-7}"/>
      </ParameterList>
      <ParameterList name="Solute BC">
        <ParameterList name="Aqueous">
          <ParameterList name="water">
            <ParameterList name="H+">
              <ParameterList name="BC: Uniform Concentration">
                <Parameter name="Geochemical Condition" type="string" value="atmosphere"/>
              </ParameterList>
              <Parameter name="Concentration Units" type="string" value="Molarity"/>
            </ParameterList>
            <ParameterList name="Cl-">
              <ParameterList name="BC: Uniform Concentration">
                <Parameter name="Geochemical Condition" type="string" value="atmosphere"/>
              </ParameterList>
              <Parameter name="Concentration Units" type="string" value="Molarity"/>
            </ParameterList>
            <ParameterList name="SO4--">
              <ParameterList name="BC: Uniform Concentration">
                <Parameter name="Geochemical Condition" type="string" value="atmosphere"/>
              </ParameterList>
              <Parameter name="Concentration Units" type="string" value="Molarity"/>
            </ParameterList>
            <ParameterList name="HCO3-">
              <ParameterList name="BC: Uniform Concentration">
                <Parameter name="Geochemical Condition" type="string" value="atmosphere"/>
              </ParameterList>
              <Parameter name="Concentration Units" type="string" value="Molarity"/>
            </ParameterList>
            <ParameterList name="SiO2(aq)">
              <ParameterList name="BC: Uniform Concentration">
                <Parameter name="Geochemical Condition" type="string" value="atmosphere"/>
              </ParameterList>
              <Parameter name="Concentration Units" type="string" value="Molarity"/>
            </ParameterList>
            <ParameterList name="Al+++">
              <ParameterList name="BC: Uniform Concentration">
                <Parameter name="Geochemical Condition" type="string" value="atmosphere"/>
              </ParameterList>
              <Parameter name="Concentration Units" type="string" value="Molarity"/>
            </ParameterList>
            <ParameterList name="Ca++">
              <ParameterList name="BC: Uniform Concentration">
                <Parameter name="Geochemical Condition" type="string" value="atmosphere"/>
              </ParameterList>
              <Parameter name="Concentration Units" type="string" value="Molarity"/>
            </ParameterList>
            <ParameterList name="Mg++">
              <ParameterList name="BC: Uniform Concentration">
                <Parameter name="Geochemical Condition" type="string" value="atmosphere"/>
              </ParameterList>
              <Parameter name="Concentration Units" type="string" value="Molarity"/>
            </ParameterList>
            <ParameterList name="Fe++">
              <ParameterList name="BC: Uniform Concentration">
                <Parameter name="Geochemical Condition" type="string" value="atmosphere"/>
              </ParameterList>
              <Parameter name="Concentration Units" type="string" value="Molarity"/>
            </ParameterList>
            <ParameterList name="Fe+++">
              <ParameterList name="BC: Uniform Concentration">
                <Parameter name="Geochemical Condition" type="string" value="atmosphere"/>
              </ParameterList>
              <Parameter name="Concentration Units" type="string" value="Molarity"/>
            </ParameterList>
            <ParameterList name="K+">
              <ParameterList name="BC: Uniform Concentration">
                <Parameter name="Geochemical Condition" type="string" value="atmosphere"/>
              </ParameterList>
              <Parameter name="Concentration Units" type="string" value="Molarity"/>
            </ParameterList>
            <ParameterList name="Na+">
              <ParameterList name="BC: Uniform Concentration">
                <Parameter name="Geochemical Condition" type="string" value="atmosphere"/>
              </ParameterList>
              <Parameter name="Concentration Units" type="string" value="Molarity"/>
            </ParameterList>
            <ParameterList name="O2(aq)">
              <ParameterList name="BC: Uniform Concentration">
                <Parameter name="Geochemical Condition" type="string" value="atmosphere"/>
              </ParameterList>
              <Parameter name="Concentration Units" type="string" value="Molarity"/>
            </ParameterList>
            <ParameterList name="HS-">
              <ParameterList name="BC: Uniform Concentration">
                <Parameter name="Geochemical Condition" type="string" value="atmosphere"/>
              </ParameterList>
              <Parameter name="Concentration Units" type="string" value="Molarity"/>
            </ParameterList>
            <ParameterList name="NO3-">
              <ParameterList name="BC: Uniform Concentration">
                <Parameter name="Geochemical Condition" type="string" value="atmosphere"/>
              </ParameterList>
              <Parameter name="Concentration Units" type="string" value="Molarity"/>
            </ParameterList>
            <ParameterList name="NO2-">
              <ParameterList name="BC: Uniform Concentration">
                <Parameter name="Geochemical Condition" type="string" value="atmosphere"/>
              </ParameterList>
              <Parameter name="Concentration Units" type="string" value="Molarity"/>
            </ParameterList>
            <ParameterList name="N2(aq)">
              <ParameterList name="BC: Uniform Concentration">
                <Parameter name="Geochemical Condition" type="string" value="atmosphere"/>
              </ParameterList>
              <Parameter name="Concentration Units" type="string" value="Molarity"/>
            </ParameterList>
            <ParameterList name="Ac-">
              <ParameterList name="BC: Uniform Concentration">
                <Parameter name="Geochemical Condition" type="string" value="atmosphere"/>
              </ParameterList>
              <Parameter name="Concentration Units" type="string" value="Molarity"/>
            </ParameterList>
            <ParameterList name="NH3(aq)">
              <ParameterList name="BC: Uniform Concentration">
                <Parameter name="Geochemical Condition" type="string" value="atmosphere"/>
              </ParameterList>
              <Parameter name="Concentration Units" type="string" value="Molarity"/>
            </ParameterList>
            <ParameterList name="Tracer">
              <ParameterList name="BC: Uniform Concentration">
                <Parameter name="Geochemical Condition" type="string" value="atmosphere"/>
              </ParameterList>
              <Parameter name="Concentration Units" type="string" value="Molarity"/>
            </ParameterList>
            <!--            <ParameterList name="tracer">
              <ParameterList name="BC: Uniform Concentration">
                <Parameter name="Times" type="Array(double)" value="{0.00000000000000000e+00, 4.73364001000000000e+08}"/>
                <Parameter name="Time Functions" type="Array(string)" value="{Constant}"/>
                <Parameter name="Values" type="Array(double)" value="{0.00000000000000000e+00, 0.00000000000000000e+00}"/>
              </ParameterList>
            </ParameterList> -->
          </ParameterList>
        </ParameterList>
      </ParameterList>
    </ParameterList>
    <ParameterList name="upstream">
      <Parameter name="Assigned Regions" type="Array(string)" value="{right}"/>
      <ParameterList name="BC: Hydrostatic">
        <Parameter name="Times" type="Array(double)" value="{0e-17, 473364001.000000000}"/>
        <Parameter name="Time Functions" type="Array(string)" value="{Constant}"/>
        <Parameter name="Water Table Height" type="Array(double)" value="{5.23190000000000044, 5.23190000000000044}"/>
      </ParameterList>
      <ParameterList name="Solute BC">
        <ParameterList name="Aqueous">
          <ParameterList name="water">
            <ParameterList name="H+">
              <ParameterList name="BC: Uniform Concentration">
                <Parameter name="Geochemical Condition" type="string" value="oxidizedtracer"/>
              </ParameterList>
              <Parameter name="Concentration Units" type="string" value="Molarity"/>
            </ParameterList>
            <ParameterList name="Cl-">
              <ParameterList name="BC: Uniform Concentration">
                <Parameter name="Geochemical Condition" type="string" value="oxidizedtracer"/>
              </ParameterList>
              <Parameter name="Concentration Units" type="string" value="Molarity"/>
            </ParameterList>
            <ParameterList name="SO4--">
              <ParameterList name="BC: Uniform Concentration">
                <Parameter name="Geochemical Condition" type="string" value="oxidizedtracer"/>
              </ParameterList>
              <Parameter name="Concentration Units" type="string" value="Molarity"/>
            </ParameterList>
            <ParameterList name="HCO3-">
              <ParameterList name="BC: Uniform Concentration">
                <Parameter name="Geochemical Condition" type="string" value="oxidizedtracer"/>
              </ParameterList>
              <Parameter name="Concentration Units" type="string" value="Molarity"/>
            </ParameterList>
            <ParameterList name="SiO2(aq)">
              <ParameterList name="BC: Uniform Concentration">
                <Parameter name="Geochemical Condition" type="string" value="oxidizedtracer"/>
              </ParameterList>
              <Parameter name="Concentration Units" type="string" value="Molarity"/>
            </ParameterList>
            <ParameterList name="Al+++">
              <ParameterList name="BC: Uniform Concentration">
                <Parameter name="Geochemical Condition" type="string" value="oxidizedtracer"/>
              </ParameterList>
              <Parameter name="Concentration Units" type="string" value="Molarity"/>
            </ParameterList>
            <ParameterList name="Ca++">
              <ParameterList name="BC: Uniform Concentration">
                <Parameter name="Geochemical Condition" type="string" value="oxidizedtracer"/>
              </ParameterList>
              <Parameter name="Concentration Units" type="string" value="Molarity"/>
            </ParameterList>
            <ParameterList name="Mg++">
              <ParameterList name="BC: Uniform Concentration">
                <Parameter name="Geochemical Condition" type="string" value="oxidizedtracer"/>
              </ParameterList>
              <Parameter name="Concentration Units" type="string" value="Molarity"/>
            </ParameterList>
            <ParameterList name="Fe++">
              <ParameterList name="BC: Uniform Concentration">
                <Parameter name="Geochemical Condition" type="string" value="oxidizedtracer"/>
              </ParameterList>
              <Parameter name="Concentration Units" type="string" value="Molarity"/>
            </ParameterList>
            <ParameterList name="Fe+++">
              <ParameterList name="BC: Uniform Concentration">
                <Parameter name="Geochemical Condition" type="string" value="oxidizedtracer"/>
              </ParameterList>
              <Parameter name="Concentration Units" type="string" value="Molarity"/>
            </ParameterList>
            <ParameterList name="K+">
              <ParameterList name="BC: Uniform Concentration">
                <Parameter name="Geochemical Condition" type="string" value="oxidizedtracer"/>
              </ParameterList>
              <Parameter name="Concentration Units" type="string" value="Molarity"/>
            </ParameterList>
            <ParameterList name="Na+">
              <ParameterList name="BC: Uniform Concentration">
                <Parameter name="Geochemical Condition" type="string" value="oxidizedtracer"/>
              </ParameterList>
              <Parameter name="Concentration Units" type="string" value="Molarity"/>
            </ParameterList>
            <ParameterList name="O2(aq)">
              <ParameterList name="BC: Uniform Concentration">
                <Parameter name="Geochemical Condition" type="string" value="oxidizedtracer"/>
              </ParameterList>
              <Parameter name="Concentration Units" type="string" value="Molarity"/>
            </ParameterList>
            <ParameterList name="HS-">
              <ParameterList name="BC: Uniform Concentration">
                <Parameter name="Geochemical Condition" type="string" value="oxidizedtracer"/>
              </ParameterList>
              <Parameter name="Concentration Units" type="string" value="Molarity"/>
            </ParameterList>
            <ParameterList name="NO3-">
              <ParameterList name="BC: Uniform Concentration">
                <Parameter name="Geochemical Condition" type="string" value="oxidizedtracer"/>
              </ParameterList>
              <Parameter name="Concentration Units" type="string" value="Molarity"/>
            </ParameterList>
            <ParameterList name="NO2-">
              <ParameterList name="BC: Uniform Concentration">
                <Parameter name="Geochemical Condition" type="string" value="oxidizedtracer"/>
              </ParameterList>
              <Parameter name="Concentration Units" type="string" value="Molarity"/>
            </ParameterList>
            <ParameterList name="N2(aq)">
              <ParameterList name="BC: Uniform Concentration">
                <Parameter name="Geochemical Condition" type="string" value="oxidizedtracer"/>
              </ParameterList>
              <Parameter name="Concentration Units" type="string" value="Molarity"/>
            </ParameterList>
            <ParameterList name="Ac-">
              <ParameterList name="BC: Uniform Concentration">
                <Parameter name="Geochemical Condition" type="string" value="oxidizedtracer"/>
              </ParameterList>
              <Parameter name="Concentration Units" type="string" value="Molarity"/>
            </ParameterList>
            <ParameterList name="NH3(aq)">
              <ParameterList name="BC: Uniform Concentration">
                <Parameter name="Geochemical Condition" type="string" value="oxidizedtracer"/>
              </ParameterList>
              <Parameter name="Concentration Units" type="string" value="Molarity"/>
            </ParameterList>
            <ParameterList name="Tracer">
              <ParameterList name="BC: Uniform Concentration">
                <Parameter name="Geochemical Condition" type="string" value="oxidizedtracer"/>
              </ParameterList>
              <Parameter name="Concentration Units" type="string" value="Molarity"/>
            </ParameterList>
          </ParameterList>
        </ParameterList>
      </ParameterList>
    </ParameterList>
    <ParameterList name="downstream">
      <Parameter name="Assigned Regions" type="Array(string)" value="{left}"/>
      <ParameterList name="BC: Hydrostatic">
        <Parameter name="Times" type="Array(double)" value="{0e-17, 473364001.000000000}"/>
        <Parameter name="Time Functions" type="Array(string)" value="{Constant}"/>
        <Parameter name="Water Table Height" type="Array(double)" value="{4.56250000000000000, 4.56250000000000000}"/>
      </ParameterList>
      <ParameterList name="Solute BC">
        <ParameterList name="Aqueous">
          <ParameterList name="water">
            <ParameterList name="H+">
              <ParameterList name="BC: Uniform Concentration">
                <Parameter name="Geochemical Condition" type="string" value="reduced"/>
              </ParameterList>
              <Parameter name="Concentration Units" type="string" value="Molarity"/>
            </ParameterList>
            <ParameterList name="Cl-">
              <ParameterList name="BC: Uniform Concentration">
                <Parameter name="Geochemical Condition" type="string" value="reduced"/>
              </ParameterList>
              <Parameter name="Concentration Units" type="string" value="Molarity"/>
            </ParameterList>
            <ParameterList name="SO4--">
              <ParameterList name="BC: Uniform Concentration">
                <Parameter name="Geochemical Condition" type="string" value="reduced"/>
              </ParameterList>
              <Parameter name="Concentration Units" type="string" value="Molarity"/>
            </ParameterList>
            <ParameterList name="HCO3-">
              <ParameterList name="BC: Uniform Concentration">
                <Parameter name="Geochemical Condition" type="string" value="reduced"/>
              </ParameterList>
              <Parameter name="Concentration Units" type="string" value="Molarity"/>
            </ParameterList>
            <ParameterList name="SiO2(aq)">
              <ParameterList name="BC: Uniform Concentration">
                <Parameter name="Geochemical Condition" type="string" value="reduced"/>
              </ParameterList>
              <Parameter name="Concentration Units" type="string" value="Molarity"/>
            </ParameterList>
            <ParameterList name="Al+++">
              <ParameterList name="BC: Uniform Concentration">
                <Parameter name="Geochemical Condition" type="string" value="reduced"/>
              </ParameterList>
              <Parameter name="Concentration Units" type="string" value="Molarity"/>
            </ParameterList>
            <ParameterList name="Ca++">
              <ParameterList name="BC: Uniform Concentration">
                <Parameter name="Geochemical Condition" type="string" value="reduced"/>
              </ParameterList>
              <Parameter name="Concentration Units" type="string" value="Molarity"/>
            </ParameterList>
            <ParameterList name="Mg++">
              <ParameterList name="BC: Uniform Concentration">
                <Parameter name="Geochemical Condition" type="string" value="reduced"/>
              </ParameterList>
              <Parameter name="Concentration Units" type="string" value="Molarity"/>
            </ParameterList>
            <ParameterList name="Fe++">
              <ParameterList name="BC: Uniform Concentration">
                <Parameter name="Geochemical Condition" type="string" value="reduced"/>
              </ParameterList>
              <Parameter name="Concentration Units" type="string" value="Molarity"/>
            </ParameterList>
            <ParameterList name="Fe+++">
              <ParameterList name="BC: Uniform Concentration">
                <Parameter name="Geochemical Condition" type="string" value="reduced"/>
              </ParameterList>
              <Parameter name="Concentration Units" type="string" value="Molarity"/>
            </ParameterList>
            <ParameterList name="K+">
              <ParameterList name="BC: Uniform Concentration">
                <Parameter name="Geochemical Condition" type="string" value="reduced"/>
              </ParameterList>
              <Parameter name="Concentration Units" type="string" value="Molarity"/>
            </ParameterList>
            <ParameterList name="Na+">
              <ParameterList name="BC: Uniform Concentration">
                <Parameter name="Geochemical Condition" type="string" value="reduced"/>
              </ParameterList>
              <Parameter name="Concentration Units" type="string" value="Molarity"/>
            </ParameterList>
            <ParameterList name="O2(aq)">
              <ParameterList name="BC: Uniform Concentration">
                <Parameter name="Geochemical Condition" type="string" value="reduced"/>
              </ParameterList>
              <Parameter name="Concentration Units" type="string" value="Molarity"/>
            </ParameterList>
            <ParameterList name="HS-">
              <ParameterList name="BC: Uniform Concentration">
                <Parameter name="Geochemical Condition" type="string" value="reduced"/>
              </ParameterList>
              <Parameter name="Concentration Units" type="string" value="Molarity"/>
            </ParameterList>
            <ParameterList name="NO3-">
              <ParameterList name="BC: Uniform Concentration">
                <Parameter name="Geochemical Condition" type="string" value="reduced"/>
              </ParameterList>
              <Parameter name="Concentration Units" type="string" value="Molarity"/>
            </ParameterList>
            <ParameterList name="NO2-">
              <ParameterList name="BC: Uniform Concentration">
                <Parameter name="Geochemical Condition" type="string" value="reduced"/>
              </ParameterList>
              <Parameter name="Concentration Units" type="string" value="Molarity"/>
            </ParameterList>
            <ParameterList name="N2(aq)">
              <ParameterList name="BC: Uniform Concentration">
                <Parameter name="Geochemical Condition" type="string" value="reduced"/>
              </ParameterList>
              <Parameter name="Concentration Units" type="string" value="Molarity"/>
            </ParameterList>
            <ParameterList name="Ac-">
              <ParameterList name="BC: Uniform Concentration">
                <Parameter name="Geochemical Condition" type="string" value="reduced"/>
              </ParameterList>
              <Parameter name="Concentration Units" type="string" value="Molarity"/>
            </ParameterList>
            <ParameterList name="NH3(aq)">
              <ParameterList name="BC: Uniform Concentration">
                <Parameter name="Geochemical Condition" type="string" value="reduced"/>
              </ParameterList>
              <Parameter name="Concentration Units" type="string" value="Molarity"/>
            </ParameterList>
            <ParameterList name="Tracer">
              <ParameterList name="BC: Uniform Concentration">
                <Parameter name="Geochemical Condition" type="string" value="reduced"/>
              </ParameterList>
              <Parameter name="Concentration Units" type="string" value="Molarity"/>
            </ParameterList>
          </ParameterList>
        </ParameterList>
      </ParameterList>
    </ParameterList>
  </ParameterList>
  <ParameterList name="Sources">
  </ParameterList>
  <ParameterList name="Output">
    <ParameterList name="Time Macros">
      <ParameterList name="Time Output">
        <Parameter name="Values" type="Array(double)" value="{8.63713e+6, 63110000.0000000000, 126200000.000000000, 189300000.000000000, 252500000.000000000, 315600000.000000000, 378700000.000000000, 441800000.000000000}"/>
      </ParameterList>
    </ParameterList>
    <ParameterList name="Cycle Macros">
      <ParameterList name="Every_50_timesteps">
        <Parameter name="Start_Period_Stop" type="Array(int)" value="{0, 50, -1}"/>
      </ParameterList>
    </ParameterList>
    <ParameterList name="Checkpoint Data">
      <Parameter name="File Name Base" type="string" value="chk"/>
      <Parameter name="File Name Digits" type="int" value="5"/>
      <Parameter name="Cycle Macro" type="string" value="Every_50_timesteps"/>
    </ParameterList>
    <ParameterList name="Visualization Data">
      <Parameter name="File Name Base" type="string" value="plot_new"/>
      <Parameter name="File Name Digits" type="int" value="5"/>
      <Parameter name="Time Macros" type="Array(string)" value="{Time Output}"/>
    </ParameterList>
  </ParameterList>
  <ParameterList name="Chemistry">
    <Parameter name="Engine" type="string" value="PFloTran"/>
    <Parameter name="Engine Input File" type="string" value="rifle-arora-spycher.in"/>
    <Parameter name="Verbosity" type="string" value="high"/>
    <!-- timestep control -->
    <Parameter name="Initial Time Step (s)" type="double" value="5.0"/>
    <Parameter name="Time Step Control Method" type="string" value="simple"/>
    <!-- default is fixed -->
    <Parameter name="Time Step Cut Threshold" type="int" value="8"/>
    <!-- default is 8     -->
    <Parameter name="Time Step Cut Factor" type="double" value="2.0"/>
    <!-- default is 2.0   -->
    <Parameter name="Time Step Increase Threshold" type="int" value="4"/>
    <!-- default is 4     -->
    <Parameter name="Time Step Increase Factor" type="double" value="1.2"/>
    <!-- default is 1.2   -->
    <Parameter name="Max Time Step (s)" type="double" value="1e+5"/>
  </ParameterList>
  <!-- Chemistry -->
</ParameterList>
